{
    "Ar36": {
        "error": 0.00091662125413645499, 
        "fit": "Parabolic", 
        "value": 0.00083975355774567597
    }, 
    "Ar37": {
        "error": 0.12477408529729971, 
        "fit": "linear", 
        "value": -0.010283341386246141
    }, 
    "Ar38": {
        "error": 0.10911236842637202, 
        "fit": "linear", 
        "value": -0.093408116706671526
    }, 
    "Ar39": {
        "error": 0.048739033362565388, 
        "fit": "Parabolic", 
        "value": -0.058602172394766686
    }, 
    "Ar40": {
        "error": 0.10291589067805286, 
        "fit": "Parabolic", 
        "value": 0.083815390560020103
    }, 
    "Ar41": {
        "error": 0.09714049848100699, 
        "fit": "linear", 
        "value": 0.0078641908315794044
    }
}