{
    "AX": {
        "error": 0.056314200091282726, 
        "fit": "average_SEM", 
        "value": -0.013163574731152039
    }, 
    "CDD": {
        "error": 0.00020518396092702017, 
        "fit": "average_SEM", 
        "value": 0.0002717212604238739
    }, 
    "H1": {
        "error": 0.11786779481689957, 
        "fit": "average_SEM", 
        "value": -0.00109808046836406
    }, 
    "H2": {
        "error": 0.12441180637667414, 
        "fit": "average_SEM", 
        "value": -0.025752936606295407
    }, 
    "L1": {
        "error": 0.11218375652505438, 
        "fit": "average_SEM", 
        "value": -0.054620327412521874
    }, 
    "L2": {
        "error": 0.1222647569133779, 
        "fit": "average_SEM", 
        "value": -0.03873488852356483
    }
}