{
    "Ar36": {
        "error": 0.013261183602615181, 
        "fit": "parabolic", 
        "value": 1.223121552181432
    }, 
    "Ar37": {
        "error": 0.15690194122815035, 
        "fit": "linear", 
        "value": 30.09214229468278
    }, 
    "Ar38": {
        "error": 0.11676333936148382, 
        "fit": "linear", 
        "value": 1.3549241304442954
    }, 
    "Ar39": {
        "error": 0.075053550836843577, 
        "fit": "parabolic", 
        "value": 32.084580243130297
    }, 
    "Ar40": {
        "error": 0.24054101225376762, 
        "fit": "parabolic", 
        "value": 368.3523651579377
    }, 
    "Ar41": {
        "error": 0.1102495680884852, 
        "fit": "average_SEM", 
        "value": -0.025682133376321872
    }
}