{
    "Ar36": {
        "error": 0.020635488785412062, 
        "fit": "Parabolic", 
        "value": 3.7063716022248023
    }, 
    "Ar37": {
        "error": 0.12200600945828993, 
        "fit": "linear", 
        "value": -0.0023838366753469627
    }, 
    "Ar38": {
        "error": 0.099116543321784017, 
        "fit": "linear", 
        "value": 0.63312523774677443
    }, 
    "Ar39": {
        "error": 0.057099397253039592, 
        "fit": "Parabolic", 
        "value": -0.053756826791626487
    }, 
    "Ar40": {
        "error": 0.33577407401996212, 
        "fit": "Parabolic", 
        "value": 1127.7231422740899
    }, 
    "Ar41": {
        "error": 0.10485931986089475, 
        "fit": "linear", 
        "value": 0.00986346754970833
    }
}