{
    "Ar36": {
        "error": 0.019890422355285719, 
        "fit": "Parabolic", 
        "value": 3.763758877499261
    }, 
    "Ar37": {
        "error": 0.11943696820699812, 
        "fit": "linear", 
        "value": 2.6758297802015472
    }, 
    "Ar38": {
        "error": 0.10895600431735891, 
        "fit": "linear", 
        "value": 0.97897946393925817
    }, 
    "Ar39": {
        "error": 0.055289511328457774, 
        "fit": "Parabolic", 
        "value": 10.027094620136971
    }, 
    "Ar40": {
        "error": 0.36289161620100258, 
        "fit": "Parabolic", 
        "value": 1138.5558778599916
    }, 
    "Ar41": {
        "error": 0.096858567482297889, 
        "fit": "linear", 
        "value": 0.010284860125372067
    }
}